gemini_ai_helper/__init__.py
gemini_ai_helper/core.py
gemini_ai_helper/utils.py
gemini_ai_helper_febin-0.1.2.dist-info/METADATA
gemini_ai_helper_febin-0.1.2.dist-info/WHEEL
gemini_ai_helper_febin-0.1.2.dist-info/top_level.txt
gemini_ai_helper_febin-0.1.2.dist-info/RECORD
