Metadata-Version: 2.4
Name: gemini-ai-helper-febin
Version: 0.1.2
Summary: Gemini AI response and summarization library
Author: Febin Sunny
Requires-Python: >=3.8
Requires-Dist: google-generativeai
